<?xml version="1.0"?>
<configuration>
  <!-- 
  <property>
    <name>dt.application.{appName}.operator.{opName}.prop.{propName}</name>
    <value>some-default-value (if value is not specified, it is required from the user or custom config when launching)</value>
  </property>
  -->
  <!-- memory assigned to app master
  <property>
    <name>dt.attr.MASTER_MEMORY_MB</name>
    <value>1024</value>
  </property>
  -->

  <!-- unused but necessary -->
  <property>
    <name>dt.application.FileIO.operator.read.prop.directory</name>
    <value>/tmp/fileIO/dummy</value>
  </property>

  <property>
    <name>dt.application.FileIO.operator.read.prop.directories</name>
    <value>"/tmp/fileIO/in1","/tmp/fileIO/in2"</value>
  </property>

  <property>
    <name>dt.application.FileIO.operator.read.prop.partitionCounts</name>
    <value>2,3</value>
  </property>

  <property>
   <name>dt.application.FileIO.operator.read.attr.MEMORY_MB</name>
   <value>512</value>
  </property>

  <property>
   <name>dt.application.FileIO.operator.write.attr.MEMORY_MB</name>
   <value>512</value>
  </property>

  <property>
    <name>dt.application.FileIO.operator.*.port.*.attr.BUFFER_MEMORY_MB</name>
    <value>128</value>
  </property>

  <property>
   <name>dt.application.FileIO.stream.data.locality</name>
   <value>CONTAINER_LOCAL</value>
  </property>

  <property>
   <name>dt.application.FileIO.stream.control.locality</name>
   <value>CONTAINER_LOCAL</value>
  </property>

  <property>
    <name>dt.application.FileIO.operator.write.prop.filePath</name>
    <value>/tmp/fileIO/output-dir</value>
  </property>

  <property>
    <name>dt.loggers.level</name>
    <value>com.datatorrent.*:INFO,org.apache.*:INFO</value>
  </property>
</configuration>

